Metadata-Version: 1.1
Name: pyacd
Version: 0.2.0
Summary: python API to EMBOSS ACD files
Home-page: https://github.com/hmenager/pyacd.git
Author: Hervé Ménager
Author-email: hmenager@pasteur.fr
License: BSD
Download-URL: https://github.com/hmenager/pyacd/tarball/0.1
Platform: UNKNOWN
